iustus/__init__.py
iustus-0.0.1.dist-info/METADATA
iustus-0.0.1.dist-info/WHEEL
iustus-0.0.1.dist-info/top_level.txt
iustus-0.0.1.dist-info/RECORD
