Metadata-Version: 2.4
Name: iustus
Version: 0.0.1
Summary: Justus-based semantic kernel for structural curvature modeling
Author-email: Chae Yeon Xon <your@email.com>
License: MIT
Classifier: Programming Language :: Python :: 3
Classifier: License :: OSI Approved :: MIT License
Classifier: Operating System :: OS Independent
Requires-Python: >=3.8
